{
  "tweet": "1653025474489073664",
  "retweeters": [
    {
      "name": "AnindaGoswamy",
      "id": 990606871785623552
    },
    {
      "name": "danrhowarth",
      "id": 451721594
    },
    {
      "name": "LucianMaly",
      "id": 33468259
    },
    {
      "name": "pannaga30",
      "id": 3313283834
    },
    {
      "name": "ashishtele1",
      "id": 755627976
    },
    {
      "name": "Petit2411",
      "id": 277699447
    },
    {
      "name": "Pradee__007",
      "id": 1371385383796178944
    },
    {
      "name": "subhobrata1",
      "id": 200181730
    },
    {
      "name": "mathgril",
      "id": 755098462690082817
    },
    {
      "name": "Judy_Hooopps",
      "id": 1433931524186034176
    },
    {
      "name": "16danielvm",
      "id": 1255734295597064192
    },
    {
      "name": "WearsTheFoxHat_",
      "id": 133430119
    },
    {
      "name": "oladii1",
      "id": 227855329
    }
  ]
}